LICENSE.txt
README.md
setup.py
firmiana/__init__.py
firmiana/__version__.py
firmiana/main.py
firmiana.egg-info/PKG-INFO
firmiana.egg-info/SOURCES.txt
firmiana.egg-info/dependency_links.txt
firmiana.egg-info/top_level.txt
firmiana/backbone/__init__.py
firmiana/environment/__init__.py
firmiana/environment/application/__init__.py
firmiana/environment/dataset/__init__.py
firmiana/environment/paradigm/__init__.py
firmiana/environment/setting/__init__.py
firmiana/method/__init__.py
firmiana/utils/__init__.py
firmiana/utils/buffer_memory.py
firmiana/utils/metrics.py
test/test_pypi.py