Metadata-Version: 2.1
Name: firmiana
Version: 0.0.4
Summary: A playground for research at the interaction of continual learning and natural language processing.
Home-page: https://github.com/wutong8023/Firmiana
Author: Tongtong Wu
Author-email: wutong8023@gmail.com
License: MIT
Platform: UNKNOWN
Classifier: License :: OSI Approved :: MIT License
Classifier: Programming Language :: Python
Classifier: Programming Language :: Python :: 3
Classifier: Programming Language :: Python :: 3.6
Classifier: Programming Language :: Python :: Implementation :: CPython
Classifier: Programming Language :: Python :: Implementation :: PyPy
Requires-Python: >=3.4.0
License-File: LICENSE.txt
